synthba/__init__.py
synthba/cli.py
synthba/registration.py
synthba/skull_stripping.py
synthba/synthba.py
synthba-0.1.0.dist-info/METADATA
synthba-0.1.0.dist-info/WHEEL
synthba-0.1.0.dist-info/entry_points.txt
synthba-0.1.0.dist-info/top_level.txt
synthba-0.1.0.dist-info/RECORD
