Metadata-Version: 2.4
Name: synthba
Version: 0.1.0
Summary: SynthBA: Reliable Brain Age Estimation Across Multiple MRI Sequences and Resolutions
Author-email: Lemuel Puglisi <lemuelpuglisi001@gmail.com>
Classifier: Programming Language :: Python :: 3
Classifier: License :: OSI Approved :: MIT License
Classifier: Operating System :: OS Independent
Requires-Python: >=3.9
Requires-Dist: pandas==2.*
Requires-Dist: nibabel==5.*
Requires-Dist: torch==2.*
Requires-Dist: monai==1.*
Requires-Dist: huggingface-hub==0.*
Requires-Dist: scipy==1.*
Requires-Dist: numpy==1.*
Requires-Dist: antspyx==0.*
